signicat_api/__init__.py
signicat_api/api.py
signicat_api/request_types.py
signicat_api-1.2.7.dist-info/METADATA
signicat_api-1.2.7.dist-info/WHEEL
signicat_api-1.2.7.dist-info/top_level.txt
signicat_api-1.2.7.dist-info/RECORD
